odoo9_addon_partner_street_number-9.0.0.1.0.99.dev1-py2.7-nspkg.pth
odoo9_addon_partner_street_number-9.0.0.1.0.99.dev1.dist-info/METADATA
odoo9_addon_partner_street_number-9.0.0.1.0.99.dev1.dist-info/RECORD
odoo9_addon_partner_street_number-9.0.0.1.0.99.dev1.dist-info/WHEEL
odoo9_addon_partner_street_number-9.0.0.1.0.99.dev1.dist-info/namespace_packages.txt
odoo9_addon_partner_street_number-9.0.0.1.0.99.dev1.dist-info/top_level.txt
odoo_addons/partner_street_number/README.rst
odoo_addons/partner_street_number/__init__.py
odoo_addons/partner_street_number/__openerp__.py
odoo_addons/partner_street_number/i18n/es.po
odoo_addons/partner_street_number/i18n/nl.po
odoo_addons/partner_street_number/i18n/partner_street_number.pot
odoo_addons/partner_street_number/i18n/pt_BR.po
odoo_addons/partner_street_number/i18n/sl.po
odoo_addons/partner_street_number/models/__init__.py
odoo_addons/partner_street_number/models/res_partner.py
odoo_addons/partner_street_number/static/description/icon.png
odoo_addons/partner_street_number/static/description/icon.svg
odoo_addons/partner_street_number/static/src/css/field.css
odoo_addons/partner_street_number/views/assets.xml
odoo_addons/partner_street_number/views/res_partner.xml
