Metadata-Version: 2.1
Name: odoo9-addon-partner-street-number
Version: 9.0.0.1.0.99.dev1
Summary: Introduces separate fields for street name and street number.
Home-page: https://github.com/oca/partner-contact
Author: Therp BV,Odoo Community Association (OCA)
Author-email: support@odoo-community.org
License: AGPL-3
Platform: UNKNOWN
Classifier: Programming Language :: Python
Classifier: Framework :: Odoo
Classifier: License :: OSI Approved :: GNU Affero General Public License v3
Requires-Python: ~=2.7
Requires-Dist: odoo (<9.1a,>=9.0a)
